.hgignore
CHANGES.txt
LICENSE.txt
README.txt
bootstrap.py
bootstrap.pyo
buildout.cfg
setup.py
js/__init__.py
js.json2.egg-info/PKG-INFO
js.json2.egg-info/SOURCES.txt
js.json2.egg-info/dependency_links.txt
js.json2.egg-info/entry_points.txt
js.json2.egg-info/namespace_packages.txt
js.json2.egg-info/not-zip-safe
js.json2.egg-info/requires.txt
js.json2.egg-info/top_level.txt
js/json2/__init__.py
js/json2/test_json2.txt
js/json2/resources/README.txt
js/json2/resources/json2.js