Metadata-Version: 1.0
Name: js.json2
Version: 2011-02-23
Summary: Fanstatic packaging of jQuery JSON
Home-page: UNKNOWN
Author: Fanstatic Developers
Author-email: fanstatic@googlegroups.com
License: BSD
Platform: UNKNOWN
